ZBRO3/__init__.py
ZBRO3-0.22.228.dist-info/METADATA
ZBRO3-0.22.228.dist-info/WHEEL
ZBRO3-0.22.228.dist-info/top_level.txt
ZBRO3-0.22.228.dist-info/RECORD
