Metadata-Version: 2.1
Name: ZBRO3
Version: 0.22.228
Summary: Lobby bot.
Home-page: https://www.youtube.com
Author: Sekkay
Classifier: Programming Language :: Python :: 3
Classifier: License :: OSI Approved :: MIT License
Classifier: Operating System :: OS Independent
Requires-Dist: crayons
Requires-Dist: fortnitepy (==3.6.7)
Requires-Dist: BenBotAsync
Requires-Dist: FortniteAPIAsync
Requires-Dist: uvloop
Requires-Dist: sanic (==21.6.2)
Requires-Dist: colorama
Requires-Dist: aiohttp
